pixtreme_aces/__init__.py
pixtreme_aces/encoding.py
pixtreme_aces/eotf.py
pixtreme_aces/matrix.py
pixtreme_aces/transform.py
pixtreme_aces-0.8.6.dist-info/METADATA
pixtreme_aces-0.8.6.dist-info/WHEEL
pixtreme_aces-0.8.6.dist-info/licenses/LICENSE
pixtreme_aces-0.8.6.dist-info/RECORD
