Metadata-Version: 2.4
Name: pixtreme-aces
Version: 0.8.6
Summary: ACES color management for pixtreme (OCIO ACES 1.2 compliant)
Project-URL: repository, https://github.com/sync-dev-org/pixtreme
Project-URL: issues, https://github.com/sync-dev-org/pixtreme/issues
Author-email: minamik <mia@sync.dev>
License-Expression: MIT
License-File: LICENSE
Classifier: Development Status :: 4 - Beta
Classifier: Environment :: GPU :: NVIDIA CUDA :: 12
Classifier: Intended Audience :: Developers
Classifier: License :: OSI Approved :: MIT License
Classifier: Operating System :: Microsoft :: Windows
Classifier: Operating System :: POSIX :: Linux
Classifier: Programming Language :: Python :: 3.12
Classifier: Programming Language :: Python :: 3.13
Classifier: Topic :: Multimedia :: Graphics
Classifier: Topic :: Multimedia :: Video
Classifier: Topic :: Software Development :: Libraries
Requires-Python: >=3.12
Requires-Dist: pixtreme-core>=0.8.6
